Metadata-Version: 2.0
Name: odoo10-addon-report-qweb-operating-unit
Version: 10.0.1.0.0
Summary: Qweb Report With Operating Unit
Home-page: https://odoo-community.org/
Author: Eficent Business and IT Consulting Services S.L., Serpent Consulting Services Pvt. Ltd.,Odoo Community Association (OCA)
Author-email: support@odoo-community.org
License: AGPL-3
Platform: UNKNOWN
Classifier: Programming Language :: Python
Classifier: Framework :: Odoo
Classifier: License :: OSI Approved :: GNU Affero General Public License v3
Requires-Python: ~=2.7
Requires-Dist: odoo (<10.1dev,>=10.0)
Requires-Dist: odoo10-addon-operating-unit
